curve_tracer/__init__.py
curve_tracer/__main__.py
curve_tracer/about.py
curve_tracer/app.py
curve_tracer/plot4q.py
curve_tracer/shortcut_bar.py
curve_tracer/status_bar.py
curve_tracer/version.py
curve_tracer/images/btn-erase.png
curve_tracer/images/btn-load.png
curve_tracer/images/btn-pause.png
curve_tracer/images/btn-run.png
curve_tracer/images/btn-save.png
curve_tracer/images/btn-waveform.png
curve_tracer/images/connections.png
curve_tracer/images/forembed.ico
curve_tracer/images/forembed.png
curve_tracer/images/gate-voltage.png
curve_tracer/images/select-output.png
curve_tracer/images/waveform.png
curve_tracer-0.1.0.dist-info/DESCRIPTION.rst
curve_tracer-0.1.0.dist-info/METADATA
curve_tracer-0.1.0.dist-info/RECORD
curve_tracer-0.1.0.dist-info/WHEEL
curve_tracer-0.1.0.dist-info/entry_points.txt
curve_tracer-0.1.0.dist-info/metadata.json
curve_tracer-0.1.0.dist-info/top_level.txt
