Metadata-Version: 2.0
Name: curve-tracer
Version: 0.1.0
Summary: Curve Tracer
Home-page: https://github.com/slightlynybbled/curve_tracer_gui
Author: Jason R. Jones
Author-email: slightlynybbled@gmail.com
License: MIT
Requires-Dist: pillow
Requires-Dist: serialdispatch
